Xsinfo/__init__.py
Xsinfo/xsinfo.py
Xsinfo/script/__init__.py
Xsinfo/script/_standalone_xsinfo.py
Xsinfo/test/snap.txt
Xsinfo-1.2.dist-info/METADATA
Xsinfo-1.2.dist-info/WHEEL
Xsinfo-1.2.dist-info/entry_points.txt
Xsinfo-1.2.dist-info/top_level.txt
Xsinfo-1.2.dist-info/RECORD
