Metadata-Version: 2.1
Name: Xsinfo
Version: 1.2
Summary: Xsinfo is a command line tool summarizing the nodes and cores availability on a scheduler using SLURM.
Home-page: https://github.com/FranckLejzerowicz/Xsinfo
Author: Franck Lejzerowicz
Author-email: franck.lejzerowicz@gmail.com
Maintainer: Franck Lejzerowicz
Maintainer-email: franck.lejzerowicz@gmail.com
License: BSD
Platform: UNKNOWN
Classifier: License :: OSI Approved :: BSD License
Classifier: Topic :: Scientific/Engineering
Classifier: Topic :: Scientific/Engineering :: Bio-Informatics
Classifier: Programming Language :: Python :: 3
Classifier: Programming Language :: Python :: 3 :: Only
Classifier: Operating System :: Unix
Classifier: Operating System :: POSIX
Classifier: Operating System :: MacOS :: MacOS X
Requires-Python: >=3.6
Requires-Dist: click
Requires-Dist: pandas
